setup.py
shinkenplugins/__init__.py
shinkenplugins.plugins.http_load.egg-info/PKG-INFO
shinkenplugins.plugins.http_load.egg-info/SOURCES.txt
shinkenplugins.plugins.http_load.egg-info/dependency_links.txt
shinkenplugins.plugins.http_load.egg-info/entry_points.txt
shinkenplugins.plugins.http_load.egg-info/namespace_packages.txt
shinkenplugins.plugins.http_load.egg-info/requires.txt
shinkenplugins.plugins.http_load.egg-info/top_level.txt
shinkenplugins/plugins/__init__.py
shinkenplugins/plugins/http_load/__init__.py
shinkenplugins/plugins/http_load/http_load.py