Metadata-Version: 1.0
Name: shinkenplugins.plugins.http-load
Version: 1.0
Summary: A plugin to check the average response time of a http service under moderate load
Home-page: https://github.com/savoirfairelinux/sfl-shinken-plugins
Author: Frédéric Vachon
Author-email: frederic.vachon@savoirfairelinux.com
License: GPL3+
Platform: any
